fullAdder/fullAdder.v
`timescale 1ns/1ps
module full_adder (
    input a,
    input b,
    input c_in,
    output wire sum,
    output wire carry_out
);

assign sum = a ^ b ^ c_in;

assign carry_out = (a&b) | (b&c_in) | (c_in&a);

endmodule

fullAdder/fullAdderTB.v
`timescale 1ns / 1ps
module tb_full_adder;

 reg a, b ,c_in;
 wire sum, carry_out;

 full_adder dut (a, b, c_in, sum, carry_out);

 //waveform
 initial begin
    $dumpfile("fullAdderTB.vcd");
    $dumpvars(0, tb_full_adder);
 end

 initial begin
    $display("Testing Full Adder");
    $monitor ("a=%b, b=%b, c_in=%b, sum=%b, carry_out=%b", a, b, c_in, sum, carry_out);

    //Applying test cases
    a=0; b=0; c_in=0; #10; //answers s=0 , c=0
    a=0; b=0; c_in=1; #10; //answers s=1 , c=0
    a=0; b=1; c_in=0; #10; //answers s=1 , c=0
    a=0; b=1; c_in=1; #10; //answers s=0 , c=1
    a=1; b=0; c_in=0; #10; //answers s=1 , c=0
    a=1; b=0; c_in=1; #10; //answers s=0 , c=1
    a=1; b=1; c_in=0; #10; //answers s=0 , c=1
    a=1; b=1; c_in=1; #10; //answers s=1 , c=1
    
    $finish;
 end
endmodule

fullAdder/fullAdderTB.vcd
$date
	Sun Feb 15 00:53:22 2026
$end
$version
	Icarus Verilog
$end
$timescale
	1ps
$end
$scope module tb_full_adder $end
$var wire 1 ! carry_out $end
$var wire 1 " sum $end
$var reg 1 # a $end
$var reg 1 $ b $end
$var reg 1 % c_in $end
$scope module dut $end
$var wire 1 & a $end
$var wire 1 ' b $end
$var wire 1 ( c_in $end
$var wire 1 ! carry_out $end
$var wire 1 " sum $end
$upscope $end
$upscope $end
$enddefinitions $end
#0
$dumpvars
0(
0'
0&
0%
0$
0#
0"
0!
$end
#10000
1"
1%
1(
#20000
0%
0(
1$
1'
#30000
1!
0"
1%
1(
#40000
0!
1"
0%
0(
0$
0'
1#
1&
#50000
1!
0"
1%
1(
#60000
0%
0(
1$
1'
#70000
1"
1%
1(
