16-bit Multiply-Accumulate Unit/MAC.v
`timescale 1ns/1ps

module MAC_unit (
    input wire [7:0]a,
    input wire [7:0]b,
    input wire clk,
    input wire reset,
    output reg [15:0]acc
);
    parameter max = 16'hFFFF;

    always @(posedge clk or posedge reset) begin
        if (reset) begin
            acc <= 0;
        end
        else begin
            if (acc + (a * b) > max) begin
                acc <= max;
            end
            else begin
                acc <= acc + (a * b); 
            end 
        end
    end
endmodule

16-bit Multiply-Accumulate Unit/MACTB.v
`timescale 1ns/1ps
module MAC_tb;

reg [7:0] a;
reg [7:0] b;
reg clk;
reg reset;
wire [15:0] acc;

MAC_unit dut (
    .a(a),
    .b(b),
    .clk(clk),
    .reset(reset),
    .acc(acc)
    );

initial begin
    $dumpfile("MAC.vcd");
    $dumpvars(0, MAC_tb);
end

initial begin
    $display("testing MAC");
    $monitor("Time: %0t, a= %d, b= %d, acc= %d", $time, a, b, acc);

    //initialize
    clk = 0;
    reset = 1;
    a = 8'd0;
    b = 8'd0;

    #10 reset = 0;

    #10 a= 8'd10; b= 8'd10;
    #10 a= 8'd10; b= 8'd20;

    #50 $finish;
end

always 
#5 clk = ~clk;
    
endmodule

16-bit Multiply-Accumulate Unit/MAC.vcd
$date
	Thu Feb 19 11:37:10 2026
$end
$version
	Icarus Verilog
$end
$timescale
	1ps
$end
$scope module MAC_tb $end
$var wire 16 ! acc [15:0] $end
$var reg 8 " a [7:0] $end
$var reg 8 # b [7:0] $end
$var reg 1 $ clk $end
$var reg 1 % reset $end
$scope module dut $end
$var wire 8 & a [7:0] $end
$var wire 8 ' b [7:0] $end
$var wire 1 ( clk $end
$var wire 1 ) reset $end
$var reg 16 * acc [15:0] $end
$upscope $end
$upscope $end
$enddefinitions $end
#0
$dumpvars
b0 *
1)
0(
b0 '
b0 &
1%
0$
b0 #
b0 "
b0 !
$end
#5000
1$
1(
#10000
0$
0(
0%
0)
#15000
1$
1(
#20000
0$
0(
b1010 #
b1010 '
b1010 "
b1010 &
#25000
b1100100 *
b1100100 !
1$
1(
#30000
0$
0(
b10100 #
b10100 '
#35000
b100101100 *
b100101100 !
1$
1(
#40000
0$
0(
#45000
b111110100 *
b111110100 !
1$
1(
#50000
0$
0(
#55000
b1010111100 *
b1010111100 !
1$
1(
#60000
0$
0(
#65000
b1110000100 *
b1110000100 !
1$
1(
#70000
0$
0(
#75000
b10001001100 *
b10001001100 !
1$
1(
