16-bit Accumulator/Accumulator.v
//8-bit Accumulator keeps adding 8-bit inputs with a saturation at 16-bit value FFFF 

`timescale 1ns/1ps
module Accumulator (
    input wire [7:0]d,
    input wire clk,
    input wire reset,
    output reg [15:0]sum
);
    parameter max = 16'hFFFF;

    always @(posedge clk or posedge reset) begin
        if(reset) begin
            sum <= 0;
        end

        else begin 
        if (sum + d > max) begin
         sum <= max;    
        end

        else begin
            sum <= sum + d;
        end

        end

    end
endmodule

16-bit Accumulator/AccumulatorTB.v
`timescale 1ns/1ps
module Accumulator_tb;

reg [7:0] d;
reg clk; 
reg reset;
wire [15:0] sum;

Accumulator dut (
    .d(d), 
    .clk(clk), 
    .reset(reset), 
    .sum(sum)
    );

initial begin
    $dumpfile("Acc.vcd");
    $dumpvars(0, Accumulator_tb);
 end

initial begin
    $display("testing accumulator");
    $monitor("time=%0t, d= %d, sum=%d", $time, d, sum);
    //initialize
    clk = 0;
    reset = 1;
    d = 0;

    #10; 
    reset = 0;

    #10 d= 8'd10; //
    #10 d= 8'd20;
    #10 d= 8'd30;
    #10 d= 8'd255;
    #10 d= 8'd255;

    #900 $finish;
end

//clock
always 
  #5 clk = ~clk;
    
endmodule

16-bit Accumulator/Acc.vcd
$date
	Wed Feb 18 23:08:54 2026
$end
$version
	Icarus Verilog
$end
$timescale
	1ps
$end
$scope module Accumulator_tb $end
$var wire 16 ! sum [15:0] $end
$var reg 1 " clk $end
$var reg 8 # d [7:0] $end
$var reg 1 $ reset $end
$scope module dut $end
$var wire 1 % clk $end
$var wire 8 & d [7:0] $end
$var wire 1 ' reset $end
$var reg 16 ( sum [15:0] $end
$upscope $end
$upscope $end
$enddefinitions $end
#0
$dumpvars
b0 (
1'
b0 &
0%
1$
b0 #
0"
b0 !
$end
#5000
1"
1%
#10000
0"
0%
0$
0'
#15000
1"
1%
#20000
0"
0%
b1010 #
b1010 &
#25000
b1010 (
b1010 !
1"
1%
#30000
0"
0%
b10100 #
b10100 &
#35000
b11110 (
b11110 !
1"
1%
#40000
0"
0%
b11110 #
b11110 &
#45000
b111100 (
b111100 !
1"
1%
#50000
0"
0%
b11111111 #
b11111111 &
#55000
b100111011 (
b100111011 !
1"
1%
#60000
0"
0%
#65000
b1000111010 (
b1000111010 !
1"
1%
#70000
0"
0%
#75000
b1100111001 (
b1100111001 !
1"
1%
#80000
0"
0%
#85000
b10000111000 (
b10000111000 !
1"
1%
#90000
0"
0%
#95000
b10100110111 (
b10100110111 !
1"
1%
#100000
0"
0%
#105000
b11000110110 (
b11000110110 !
1"
1%
#110000
0"
0%
#115000
b11100110101 (
b11100110101 !
1"
1%
#120000
0"
0%
#125000
b100000110100 (
b100000110100 !
1"
1%
#130000
0"
0%
#135000
b100100110011 (
b100100110011 !
1"
1%
#140000
0"
0%
#145000
b101000110010 (
b101000110010 !
1"
1%
#150000
0"
0%
#155000
b101100110001 (
b101100110001 !
1"
1%
#160000
0"
0%
#165000
b110000110000 (
b110000110000 !
1"
1%
#170000
0"
0%
#175000
b110100101111 (
b110100101111 !
1"
1%
#180000
0"
0%
#185000
b111000101110 (
b111000101110 !
1"
1%
#190000
0"
0%
#195000
b111100101101 (
b111100101101 !
1"
1%
#200000
0"
0%
#205000
b1000000101100 (
b1000000101100 !
1"
1%
#210000
0"
0%
#215000
b1000100101011 (
b1000100101011 !
1"
1%
#220000
0"
0%
#225000
b1001000101010 (
b1001000101010 !
1"
1%
#230000
0"
0%
#235000
b1001100101001 (
b1001100101001 !
1"
1%
#240000
0"
0%
#245000
b1010000101000 (
b1010000101000 !
1"
1%
#250000
0"
0%
#255000
b1010100100111 (
b1010100100111 !
1"
1%
#260000
0"
0%
#265000
b1011000100110 (
b1011000100110 !
1"
1%
#270000
0"
0%
#275000
b1011100100101 (
b1011100100101 !
1"
1%
#280000
0"
0%
#285000
b1100000100100 (
b1100000100100 !
1"
1%
#290000
0"
0%
#295000
b1100100100011 (
b1100100100011 !
1"
1%
#300000
0"
0%
#305000
b1101000100010 (
b1101000100010 !
1"
1%
#310000
0"
0%
#315000
b1101100100001 (
b1101100100001 !
1"
1%
#320000
0"
0%
#325000
b1110000100000 (
b1110000100000 !
1"
1%
#330000
0"
0%
#335000
b1110100011111 (
b1110100011111 !
1"
1%
#340000
0"
0%
#345000
b1111000011110 (
b1111000011110 !
1"
1%
#350000
0"
0%
#355000
b1111100011101 (
b1111100011101 !
1"
1%
#360000
0"
0%
#365000
b10000000011100 (
b10000000011100 !
1"
1%
#370000
0"
0%
#375000
b10000100011011 (
b10000100011011 !
1"
1%
#380000
0"
0%
#385000
b10001000011010 (
b10001000011010 !
1"
1%
#390000
0"
0%
#395000
b10001100011001 (
b10001100011001 !
1"
1%
#400000
0"
0%
#405000
b10010000011000 (
b10010000011000 !
1"
1%
#410000
0"
0%
#415000
b10010100010111 (
b10010100010111 !
1"
1%
#420000
0"
0%
#425000
b10011000010110 (
b10011000010110 !
1"
1%
#430000
0"
0%
#435000
b10011100010101 (
b10011100010101 !
1"
1%
#440000
0"
0%
#445000
b10100000010100 (
b10100000010100 !
1"
1%
#450000
0"
0%
#455000
b10100100010011 (
b10100100010011 !
1"
1%
#460000
0"
0%
#465000
b10101000010010 (
b10101000010010 !
1"
1%
#470000
0"
0%
#475000
b10101100010001 (
b10101100010001 !
1"
1%
#480000
0"
0%
#485000
b10110000010000 (
b10110000010000 !
1"
1%
#490000
0"
0%
#495000
b10110100001111 (
b10110100001111 !
1"
1%
#500000
0"
0%
#505000
b10111000001110 (
b10111000001110 !
1"
1%
#510000
0"
0%
#515000
b10111100001101 (
b10111100001101 !
1"
1%
#520000
0"
0%
#525000
b11000000001100 (
b11000000001100 !
1"
1%
#530000
0"
0%
#535000
b11000100001011 (
b11000100001011 !
1"
1%
#540000
0"
0%
#545000
b11001000001010 (
b11001000001010 !
1"
1%
#550000
0"
0%
#555000
b11001100001001 (
b11001100001001 !
1"
1%
#560000
0"
0%
#565000
b11010000001000 (
b11010000001000 !
1"
1%
#570000
0"
0%
#575000
b11010100000111 (
b11010100000111 !
1"
1%
#580000
0"
0%
#585000
b11011000000110 (
b11011000000110 !
1"
1%
#590000
0"
0%
#595000
b11011100000101 (
b11011100000101 !
1"
1%
#600000
0"
0%
#605000
b11100000000100 (
b11100000000100 !
1"
1%
#610000
0"
0%
#615000
b11100100000011 (
b11100100000011 !
1"
1%
#620000
0"
0%
#625000
b11101000000010 (
b11101000000010 !
1"
1%
#630000
0"
0%
#635000
b11101100000001 (
b11101100000001 !
1"
1%
#640000
0"
0%
#645000
b11110000000000 (
b11110000000000 !
1"
1%
#650000
0"
0%
#655000
b11110011111111 (
b11110011111111 !
1"
1%
#660000
0"
0%
#665000
b11110111111110 (
b11110111111110 !
1"
1%
#670000
0"
0%
#675000
b11111011111101 (
b11111011111101 !
1"
1%
#680000
0"
0%
#685000
b11111111111100 (
b11111111111100 !
1"
1%
#690000
0"
0%
#695000
b100000011111011 (
b100000011111011 !
1"
1%
#700000
0"
0%
#705000
b100000111111010 (
b100000111111010 !
1"
1%
#710000
0"
0%
#715000
b100001011111001 (
b100001011111001 !
1"
1%
#720000
0"
0%
#725000
b100001111111000 (
b100001111111000 !
1"
1%
#730000
0"
0%
#735000
b100010011110111 (
b100010011110111 !
1"
1%
#740000
0"
0%
#745000
b100010111110110 (
b100010111110110 !
1"
1%
#750000
0"
0%
#755000
b100011011110101 (
b100011011110101 !
1"
1%
#760000
0"
0%
#765000
b100011111110100 (
b100011111110100 !
1"
1%
#770000
0"
0%
#775000
b100100011110011 (
b100100011110011 !
1"
1%
#780000
0"
0%
#785000
b100100111110010 (
b100100111110010 !
1"
1%
#790000
0"
0%
#795000
b100101011110001 (
b100101011110001 !
1"
1%
#800000
0"
0%
#805000
b100101111110000 (
b100101111110000 !
1"
1%
#810000
0"
0%
#815000
b100110011101111 (
b100110011101111 !
1"
1%
#820000
0"
0%
#825000
b100110111101110 (
b100110111101110 !
1"
1%
#830000
0"
0%
#835000
b100111011101101 (
b100111011101101 !
1"
1%
#840000
0"
0%
#845000
b100111111101100 (
b100111111101100 !
1"
1%
#850000
0"
0%
#855000
b101000011101011 (
b101000011101011 !
1"
1%
#860000
0"
0%
#865000
b101000111101010 (
b101000111101010 !
1"
1%
#870000
0"
0%
#875000
b101001011101001 (
b101001011101001 !
1"
1%
#880000
0"
0%
#885000
b101001111101000 (
b101001111101000 !
1"
1%
#890000
0"
0%
#895000
b101010011100111 (
b101010011100111 !
1"
1%
#900000
0"
0%
#905000
b101010111100110 (
b101010111100110 !
1"
1%
#910000
0"
0%
#915000
b101011011100101 (
b101011011100101 !
1"
1%
#920000
0"
0%
#925000
b101011111100100 (
b101011111100100 !
1"
1%
#930000
0"
0%
#935000
b101100011100011 (
b101100011100011 !
1"
1%
#940000
0"
0%
#945000
b101100111100010 (
b101100111100010 !
1"
1%
#950000
0"
0%
#955000
b101101011100001 (
b101101011100001 !
1"
1%
